setup.py
pygl/DATA_TIME.py
pygl/SONG.py
pygl/__init__.py
pygl/py2D.py
pygl_np.egg-info/PKG-INFO
pygl_np.egg-info/SOURCES.txt
pygl_np.egg-info/dependency_links.txt
pygl_np.egg-info/not-zip-safe
pygl_np.egg-info/requires.txt
pygl_np.egg-info/top_level.txt