Metadata-Version: 1.0
Name: pygl-np
Version: 15.5.122rc3
Summary: small and compact graphick distributions
Home-page: UNKNOWN
Author: UNKNOWN
Author-email: pvana621@gmail.com
License: UNKNOWN
Platform: UNKNOWN
